README.md
setup.py
py_colored_logs/__init__.py
py_colored_logs/logs.py
py_colored_logs.egg-info/PKG-INFO
py_colored_logs.egg-info/SOURCES.txt
py_colored_logs.egg-info/dependency_links.txt
py_colored_logs.egg-info/requires.txt
py_colored_logs.egg-info/top_level.txt