Metadata-Version: 2.1
Name: py-colored-logs
Version: 1.0
Summary: You will be able to color Python logs with this little module. The colorable logs are as follows: success log, warning log, error log, and info log!
Home-page: https://github.com/AndrewFox-DEV/Python-colored-logs
Author: AndrewFox_DEV
Classifier: Development Status :: 3 - Alpha
Classifier: License :: OSI Approved :: MIT License
Classifier: Programming Language :: Python :: 3
Classifier: Programming Language :: Python :: 3.6
Classifier: Programming Language :: Python :: 3.7
Classifier: Programming Language :: Python :: 3.8
Classifier: Programming Language :: Python :: 3.9
Classifier: Programming Language :: Python :: 3.10
Classifier: Programming Language :: Python :: 3.11
Classifier: Programming Language :: Python :: Implementation :: CPython
Classifier: Programming Language :: Python :: Implementation :: PyPy
